Sequential Circuits/JK flip flop/JK flip flop.srcs/sources_1/new/JK2.v
module JK2 (
    input clk,
    input j,
    input k,
    output reg Q); 
    always@(posedge clk)begin
        Q<=j&~Q|~k&Q;
    end

endmodule

Sequential Circuits/JK flip flop/JK flip flop.srcs/sources_1/new/JK_2_tb.v
`timescale 1ns / 1ps

module JK_2_tb();
reg clk,j,k;
wire Q;

JK2 uut(
    .clk(clk),
    .j(j),
    .k(k),
    .Q(Q)
);

initial begin
    clk = 0;
    forever #5 clk=~clk;
end

initial begin
    $monitor("time : %0t | J = %b K = %b Q = %b",$time,j,k,Q);
    j=0;k=0;
    #10;
    j=0;k=1;
    #20;
    j=1;k=0;
    #20;
    j=1;k=1;
    #40;
    $finish;
end
initial begin
    $dumpfile("JK2_tb.vcd");
    $dumpvars(0, JK_2_tb);
end

endmodule

Sequential Circuits/JK flip flop/JK flip flop.sim/sim_1/behav/xsim/JK2_tb.vcd
$date
   Mon Jul 21 13:47:24 2025
$end
$version
  2020.2
$end
$timescale
  1ps
$end
$scope module JK_2_tb $end
$var reg 1 ! clk $end
$var reg 1 " j $end
$var reg 1 # k $end
$var wire 1 $ Q $end
$scope module uut $end
$var wire 1 % clk $end
$var wire 1 & j $end
$var wire 1 ' k $end
$var reg 1 ( Q $end
$upscope $end
$upscope $end
$enddefinitions $end
#0
$dumpvars
0!
0"
0#
x$
0%
0&
0'
x(
$end
#5000
1!
1%
#10000
0!
1#
0%
1'
#15000
1!
0$
1%
0(
#20000
0!
0%
#25000
1!
1%
#30000
0!
1"
0#
0%
1&
0'
#35000
1!
1$
1%
1(
#40000
0!
0%
#45000
1!
1%
#50000
0!
1#
0%
1'
#55000
1!
0$
1%
0(
#60000
0!
0%
#65000
1!
1$
1%
1(
#70000
0!
0%
#75000
1!
0$
1%
0(
